file_memoizer/__init__.py
file_memoizer-0.4.0.dist-info/LICENSE
file_memoizer-0.4.0.dist-info/METADATA
file_memoizer-0.4.0.dist-info/WHEEL
file_memoizer-0.4.0.dist-info/RECORD
