Metadata-Version: 2.1
Name: file-memoizer
Version: 0.4.0
Summary: Store function results across executions using cache files
Home-page: https://github.com/lordjabez/file-memoizer
License: MIT-0
Author: Judson Neer
Author-email: judson.neer@gmail.com
Requires-Python: >=3.8.1,<3.12
Classifier: License :: Other/Proprietary License
Classifier: Programming Language :: Python :: 3
Classifier: Programming Language :: Python :: 3.9
Classifier: Programming Language :: Python :: 3.10
Classifier: Programming Language :: Python :: 3.11
Requires-Dist: cachier (>=2.1.1,<3.0.0)
Project-URL: Repository, https://github.com/lordjabez/file-memoizer
